np_workflows/__init__.py
np_workflows/experiments/__init__.py
np_workflows/experiments/dynamic_routing/__init__.py
np_workflows/experiments/dynamic_routing/main.py
np_workflows/experiments/dynamic_routing/widgets.py
np_workflows/experiments/openscope_P3/P3_workflow_widget.py
np_workflows/experiments/openscope_P3/__init__.py
np_workflows/experiments/openscope_P3/main_P3_pilot.py
np_workflows/experiments/openscope_barcode/__init__.py
np_workflows/experiments/openscope_barcode/barcode_workflow_widget.py
np_workflows/experiments/openscope_barcode/main_barcode_pilot.py
np_workflows/experiments/openscope_barcode/camstim_scripts/barcode_mapping_script.py
np_workflows/experiments/openscope_barcode/camstim_scripts/barcode_opto_script.py
np_workflows/experiments/openscope_loop/__init__.py
np_workflows/experiments/openscope_loop/loop_workflow_widget.py
np_workflows/experiments/openscope_loop/main_loop_pilot.py
np_workflows/experiments/openscope_loop/camstim_scripts/barcode_mapping_script.py
np_workflows/experiments/openscope_loop/camstim_scripts/barcode_opto_script.py
np_workflows/experiments/openscope_psycode/__init__.py
np_workflows/experiments/openscope_psycode/main_psycode_pilot.py
np_workflows/experiments/openscope_psycode/psycode_workflow_widget.py
np_workflows/experiments/openscope_v2/__init__.py
np_workflows/experiments/openscope_v2/main_v2_pilot.py
np_workflows/experiments/openscope_v2/v2_workflow_widget.py
np_workflows/experiments/openscope_vippo/__init__.py
np_workflows/experiments/openscope_vippo/main_vippo_pilot.py
np_workflows/experiments/openscope_vippo/vippo_workflow_widget.py
np_workflows/experiments/task_trained_network/__init__.py
np_workflows/experiments/task_trained_network/main_ttn_pilot.py
np_workflows/experiments/task_trained_network/ttn_session_widget.py
np_workflows/experiments/task_trained_network/ttn_stim_config.py
np_workflows/experiments/task_trained_network/camstim_scripts/make_tt_stims.py
np_workflows-1.6.91.dist-info/METADATA
np_workflows-1.6.91.dist-info/WHEEL
np_workflows-1.6.91.dist-info/entry_points.txt
np_workflows-1.6.91.dist-info/top_level.txt
np_workflows-1.6.91.dist-info/RECORD
