Metadata-Version: 2.4
Name: np-workflows
Version: 1.6.91
Summary: Ecephys and behavior workflows for the Mindscope Neuropixels team.
Author-email: Ben Hardcastle <ben.hardcastle@alleninstitute.org>
License: MIT
Project-URL: Repository, https://github.com/AllenInstitute/np_workflows
Project-URL: Issues, https://github.com/AllenInstitute/np_workflows/issues
Classifier: Programming Language :: Python :: 3
Classifier: Programming Language :: Python :: 3.11
Classifier: License :: OSI Approved :: MIT License
Classifier: Operating System :: Microsoft :: Windows
Classifier: Operating System :: POSIX :: Linux
Requires-Python: ==3.11.*
Requires-Dist: ipykernel
Requires-Dist: np-services>=0.1.69
Requires-Dist: np-session>=0.6.48
Requires-Dist: np-config>=0.4.33
Requires-Dist: ipywidgets>=7
Requires-Dist: pydantic>=2
Requires-Dist: np-tools>=0.1.24
Requires-Dist: np-jobs>=0.0.3
Requires-Dist: universal-pathlib>=0.1.0
Requires-Dist: s3fs>=2023.6.0
Requires-Dist: npc-shields>=0.1.10
Requires-Dist: jupyter-bokeh>=4.0.5
